[{"account_id": 30237211, "name": "BuLba", "games_played": 241, "wins": 132, "is_current_team_member": false}, {"account_id": 86738694, "name": "qojqva", "games_played": 223, "wins": 126, "is_current_team_member": false}, {"account_id": 19757254, "name": null, "games_played": 158, "wins": 81, "is_current_team_member": null}, {"account_id": 3916428, "name": "Jerry", "games_played": 140, "wins": 73, "is_current_team_member": false}, {"account_id": 87285329, "name": "busen", "games_played": 132, "wins": 72, "is_current_team_member": false}, {"account_id": 38515149, "name": null, "games_played": 93, "wins": 53, "is_current_team_member": null}, {"account_id": 6922000, "name": "pieliedie", "games_played": 79, "wins": 50, "is_current_team_member": false}, {"account_id": 21289303, "name": "Black^", "games_played": 74, "wins": 47, "is_current_team_member": false}, {"account_id": 96169991, "name": "Kroos", "games_played": 18, "wins": 6, "is_current_team_member": false}, {"account_id": 26771994, "name": "JerAx", "games_played": 13, "wins": 6, "is_current_team_member": false}, {"account_id": 101495620, "name": "Loda", "games_played": 9, "wins": 2, "is_current_team_member": false}, {"account_id": 76482434, "name": null, "games_played": 7, "wins": 4, "is_current_team_member": null}, {"account_id": 115975133, "name": null, "games_played": 7, "wins": 4, "is_current_team_member": null}, {"account_id": 86726887, "name": "MSS-", "games_played": 4, "wins": 2, "is_current_team_member": false}, {"account_id": 20321748, "name": "SB", "games_played": 2, "wins": 1, "is_current_team_member": false}, {"account_id": 176902957, "name": null, "games_played": 2, "wins": 0, "is_current_team_member": null}, {"account_id": 113338064, "name": null, "games_played": 2, "wins": 2, "is_current_team_member": null}, {"account_id": 132291754, "name": "IAMNOBODI", "games_played": 2, "wins": 1, "is_current_team_member": false}, {"account_id": 38628747, "name": "MoonMeander", "games_played": 2, "wins": 0, "is_current_team_member": false}, {"account_id": 86745912, "name": "rtz", "games_played": 2, "wins": 2, "is_current_team_member": false}, {"account_id": 104275965, "name": "Jubei", "games_played": 1, "wins": 0, "is_current_team_member": false}, {"account_id": 168396909, "name": null, "games_played": 1, "wins": 0, "is_current_team_member": null}, {"account_id": 152962063, "name": "miCKe", "games_played": 1, "wins": 1, "is_current_team_member": false}, {"account_id": 87197791, "name": "rmN-", "games_played": 1, "wins": 1, "is_current_team_member": false}, {"account_id": 85375207, "name": "ComeWithMe", "games_played": 1, "wins": 0, "is_current_team_member": false}, {"account_id": 4285858, "name": null, "games_played": 1, "wins": 0, "is_current_team_member": null}, {"account_id": 86793739, "name": "garter", "games_played": 1, "wins": 1, "is_current_team_member": false}, {"account_id": 86828698, "name": null, "games_played": 1, "wins": 0, "is_current_team_member": null}, {"account_id": 129610677, "name": null, "games_played": 1, "wins": 0, "is_current_team_member": null}, {"account_id": 103867263, "name": null, "games_played": 1, "wins": 1, "is_current_team_member": null}, {"account_id": 87209971, "name": null, "games_played": 1, "wins": 0, "is_current_team_member": null}, {"account_id": 10366616, "name": "Sneyking", "games_played": 1, "wins": 0, "is_current_team_member": false}, {"account_id": 54580962, "name": "iNSaNia", "games_played": 1, "wins": 1, "is_current_team_member": false}, {"account_id": 114559048, "name": "Ax.Mo", "games_played": 1, "wins": 1, "is_current_team_member": false}, {"account_id": 117015167, "name": "PABLO", "games_played": 1, "wins": 0, "is_current_team_member": false}]